sonar_client/__init__.py
sonar_client/__main__.py
sonar_client/client.py
sonar_client/defaults.py
sonar_client/exceptions.py
sonar_client/models.py
sonar_client/session.py
sonar_client-0.0.5.dist-info/METADATA
sonar_client-0.0.5.dist-info/WHEEL
sonar_client-0.0.5.dist-info/entry_points.txt
sonar_client-0.0.5.dist-info/top_level.txt
sonar_client-0.0.5.dist-info/RECORD
