Metadata-Version: 2.1
Name: sonar-client
Version: 0.0.5
Summary: Client library and CLI for sonarqube API
Home-page: UNKNOWN
License: UNKNOWN
Platform: UNKNOWN
